thds/atacama/__init__.py
thds/atacama/_attrs.py
thds/atacama/_cache.py
thds/atacama/_config.py
thds/atacama/_generic_dispatch.py
thds/atacama/_meta.py
thds/atacama/_typevars.py
thds/atacama/custom_fields.py
thds/atacama/field_transforms.py
thds/atacama/fields.py
thds/atacama/generators.py
thds/atacama/leaf.py
thds/atacama/nonempty.py
thds/atacama/py.typed
thds/atacama/schemas.py
thds_atacama-1.2.20260130200324.dist-info/METADATA
thds_atacama-1.2.20260130200324.dist-info/WHEEL
thds_atacama-1.2.20260130200324.dist-info/top_level.txt
thds_atacama-1.2.20260130200324.dist-info/RECORD
