Metadata-Version: 2.4
Name: thds.atacama
Version: 1.2.20260130200324
Summary: A Marshmallow schema generator for `attrs` classes. Inspired by `desert`.
Author-email: Trilliant Health <info@trillianthealth.com>
License: MIT
Project-URL: Repository, https://github.com/TrilliantHealth/trilliant-data-science
Requires-Python: >=3.9
Requires-Dist: attrs>=22.2.0
Requires-Dist: marshmallow>=3.1
Requires-Dist: marshmallow-enum
Requires-Dist: marshmallow-union
Requires-Dist: thds-core
Requires-Dist: typing-inspect>=0.9
